odoo/addons/l10n_es_facturae_sale_stock/README.rst
odoo/addons/l10n_es_facturae_sale_stock/__init__.py
odoo/addons/l10n_es_facturae_sale_stock/__manifest__.py
odoo/addons/l10n_es_facturae_sale_stock/i18n/l10n_es_facturae_sale_stock.pot
odoo/addons/l10n_es_facturae_sale_stock/models/__init__.py
odoo/addons/l10n_es_facturae_sale_stock/models/account_move_line.py
odoo/addons/l10n_es_facturae_sale_stock/readme/CONTRIBUTORS.md
odoo/addons/l10n_es_facturae_sale_stock/readme/DESCRIPTION.md
odoo/addons/l10n_es_facturae_sale_stock/readme/INSTALL.md
odoo/addons/l10n_es_facturae_sale_stock/static/description/icon.png
odoo/addons/l10n_es_facturae_sale_stock/static/description/index.html
odoo/addons/l10n_es_facturae_sale_stock/views/report_facturae.xml
odoo_addon_l10n_es_facturae_sale_stock-18.0.1.0.0.2.dist-info/METADATA
odoo_addon_l10n_es_facturae_sale_stock-18.0.1.0.0.2.dist-info/WHEEL
odoo_addon_l10n_es_facturae_sale_stock-18.0.1.0.0.2.dist-info/top_level.txt
odoo_addon_l10n_es_facturae_sale_stock-18.0.1.0.0.2.dist-info/RECORD
