Metadata-Version: 2.1
Name: odoo-addon-l10n_es_facturae_sale_stock
Version: 18.0.1.0.0.2
Requires-Python: >=3.10
Requires-Dist: odoo-addon-l10n_es_facturae==18.0.*
Requires-Dist: odoo-addon-stock_picking_invoice_link==18.0.*
Requires-Dist: odoo==18.0.*
Summary: Entregas en Factura-e
Home-page: https://github.com/OCA/l10n-spain
License: AGPL-3
Author: Creu Blanca, NuoBiT Solutions SL, Odoo Community Association (OCA)
Author-email: support@odoo-community.org
Classifier: Programming Language :: Python
Classifier: Framework :: Odoo
Classifier: Framework :: Odoo :: 18.0
Classifier: License :: OSI Approved :: GNU Affero General Public License v3
